[ {
  "description" : "Quiz that testing your knowledge in Vue JS framework",
  "icon" : "vue.png",
  "name" : "Vuequiz",
  "questions" : [ {
    "answears" : [ "Evan You", "Evan Me", "Bruce You", "Bruce Me" ],
    "text" : "Who is author of Vue JS?"
  }, {
    "answears" : [ "set", "reactiveSet", "refresh", "deepSet" ],
    "photo" : {
      "template" : "left",
      "url" : "reactivity.png"
    },
    "text" : "Which method should we use meanwhile problems with reactivity?"
  }, {
    "answears" : [ 3, 4, 3.5, 2 ],
    "photo" : {
      "template" : "right",
      "url" : "gui.png"
    },
    "text" : "Which version of Vue CLI provides gui panel?"
  } ]
}, {
  "description" : "Quiz that testing your knowledge in PHP",
  "icon" : "php.png",
  "name" : "Phpquiz",
  "questions" : [ {
    "answears" : [ "Scope resolution operator", "Server's value", "Easter egg" ],
    "text" : "What is T_PAAMAYIM_NEKUDOTAYIM?"
  }, {
    "answears" : [ "Disabling errors", "Overriding", "Debugging mode" ],
    "photo" : {
      "template" : "left",
      "url" : "reactivity.png"
    },
    "text" : "What is purpose of @ in Php?"
  }, {
    "answears" : [ "by count function", "by len property", "by length property", "by len method" ],
    "photo" : {
      "template" : "right",
      "url" : "gui.png"
    },
    "text" : "How to get length of an array in PHP ?"
  } ]
} ]
